<?xml version="1.0" encoding="UTF-8"?>

<!DOCTYPE mapper PUBLIC "-//mybatis.org//DTD Mapper 3.0//EN"
        "http://mybatis.org/dtd/mybatis-3-mapper.dtd">
<mapper namespace="kr.co.ibk.repository.AccountRepository">

    <sql id="Base_Column_List">
        mem.mngr_pid
        ,mem.mngr_nm
        ,mem.login_id
        ,mem.pwd
        ,mem.reg_ps_id
        ,mem.reg_dtm
        ,mem.upd_ps_id
        ,mem.upd_dtm
        ,mem.del_at
        ,mem.use_at
    </sql>
    <sql id="Default_From">
        from tbl_manager as mem
    </sql>
    <select id="selectListForPaging" parameterType="RequestList" resultType="Account">
        select
        <include refid="Base_Column_List"></include>
        <include refid="Default_From"></include>
        where mem.del_at = 'N'
        <if test="data.srchUseAt != null and data.srchUseAt != ''">
            and mem.use_at = #{data.srchUseAt}
        </if>
        <if test="data.srchWord != null and data.srchWord != ''">
            and (mem.login_id like concat('%', #{data.srchWord}, '%')
            or mem.mngr_nm like concat('%', #{data.srchWord}, '%'))
        </if>
        order by mem.mngr_pid desc
        LIMIT #{pageable.offset}, #{pageable.pageSize}
    </select>
    <select id="selectListCount" parameterType="SearchForm" resultType="java.lang.Integer">
        select
        count(*)
        <include refid="Default_From"></include>
        where mem.del_at = 'N'
        <if test="srchUseAt != null and srchUseAt != ''">
            and mem.use_at = #{srchUseAt}
        </if>
        <if test="srchWord != null and srchWord != ''">
            and (mem.login_id like concat('%', #{srchWord}, '%')
            or mem.mngr_nm like concat('%', #{srchWord}, '%'))
        </if>
    </select>
    <select id="selectList" parameterType="SearchForm" resultType="Account">
        select
        <include refid="Base_Column_List"></include>
        <include refid="Default_From"></include>
        where mem.del_at = 'N'
        <if test="srchUseAt != null and srchUseAt != ''">
            and mem.use_at = #{srchUseAt}
        </if>
        <if test="srchWord != null and srchWord != ''">
            and (mem.login_id like concat('%', #{srchWord}, '%')
            or mem.mngr_nm like concat('%', #{srchWord}, '%'))
        </if>
        order by mem.mngr_pid desc
    </select>
    <select id="getLoad" parameterType="AccountForm" resultType="Account">
        select
        <include refid="Base_Column_List"></include>
        <include refid="Default_From"></include>
        where mem.del_at = 'N'
        <if test="mngrPid != null and mngrPid != ''">
            and mem.mngr_pid = #{mngrPid}
        </if>
        <if test="loginId != null and loginId != ''">
            and mem.login_id = #{loginId}
        </if>
    </select>
    <insert id="setInsert" parameterType="AccountForm">
        insert into tbl_manager(
                                 login_id
                               , pwd
                               , reg_ps_id
                               , reg_dtm
                               , upd_ps_id
                               , upd_dtm
                               , del_at
                               , use_at
                               , mngr_nm
        ) values (
                   #{loginId,jdbcType=VARCHAR}
                 , #{pwd,jdbcType=VARCHAR}
                 , #{regPsId,jdbcType=VARCHAR}
                 , #{regDtm,jdbcType=TIMESTAMP}
                 , #{updPsId,jdbcType=VARCHAR}
                 , #{updDtm,jdbcType=TIMESTAMP}
                 , #{delAt,jdbcType=CHAR}
                 , #{useAt,jdbcType=CHAR}
                 , #{mngrNm,jdbcType=VARCHAR}
                 )
    </insert>
    <update id="setUpdateByPrimaryKeySelective" parameterType="AccountForm">
        update tbl_manager
        <set>
            <if test="loginId != null and loginId != ''">
                login_id = #{loginId,jdbcType=VARCHAR}
            </if>
            <if test="pwd != null and pwd != ''">
                , pwd = #{pwd,jdbcType=VARCHAR}
            </if>
            <if test="regPsId != null and regPsId != ''">
                , reg_ps_id = #{regPsId,jdbcType=VARCHAR}
            </if>
            <if test="regDtm != null">
                , reg_dtm = #{regDtm,jdbcType=TIMESTAMP}
            </if>
            <if test="updPsId != null and updPsId != ''">
                , upd_ps_id = #{updPsId,jdbcType=VARCHAR}
            </if>
            <if test="updDtm != null">
                , upd_dtm = #{updDtm,jdbcType=TIMESTAMP}
            </if>
            <if test="delAt != null and delAt != ''">
                , del_at = #{delAt,jdbcType=CHAR}
            </if>
            <if test="useAt != null and useAt != ''">
                , use_at = #{useAt,jdbcType=CHAR}
            </if>
            <if test="mngrNm != null and mngrNm != ''">
                , mngr_nm = #{mngrNm,jdbcType=VARCHAR}
            </if>
        </set>
        where mngr_pid = #{mngrPid}
    </update>
</mapper>