<?xml version="1.0" encoding="UTF-8"?>

<!DOCTYPE mapper PUBLIC "-//mybatis.org//DTD Mapper 3.0//EN"
        "http://mybatis.org/dtd/mybatis-3-mapper.dtd">
<mapper namespace="kr.co.ibk.repository.CardOutputRepository">
    <sql id="columns">
        co.BDGT_ITEX_FRCS_CON ,
        co.BDGT_BSNS_FRCS_CON ,
        co.BDGT_PRFR_RSN_FRCS_CON ,
        co.LEARNING_MODEL_ID ,
        co.BDGT_ITEX_FRCS_PRB_CON ,
        co.BDGT_BSNS_FRCS_PRB_CON ,
        co.BDGT_PRFR_RSN_FRCS_PRB_CON ,
        co.no as outputNo ,
        ci.*
    </sql>

    <sql id="where">
    </sql>

    <select id="getDetail" resultType="CardOutputInfo" parameterType="CardInputForm">
        select
            <include refid="columns"></include>
            , lm.ID as learningModelId
            , lm.LEARN_NAME
        from
            CARD_INPUT ci
        left join CARD_OUTPUT co ON ci.TSTM_YMD = co.TSTM_YMD
            AND ci.TSTM_NO = co.TSTM_NO
            AND ci.BRCD = co.BRCD
        left join LEARNING_MODEL lm on co.LEARNING_MODEL_ID = lm.ID
        where ci.BRCD is not null
        <choose>
            <when test="loadType != null">
                AND ci.TSTM_YMD = #{tstmYmd}
                AND ci.TSTM_NO = #{tstmNo}
                AND ci.BRCD = #{brcd}
            </when>
            <otherwise>
                AND ci.NO = #{no}
            </otherwise>
        </choose>
    </select>

    <update id="updateHitYn">
        UPDATE CARD_OUTPUT co
            LEFT JOIN CARD_LEARNING_DATA cld
        ON co.TSTM_YMD = cld.TSTM_YMD
            AND co.TSTM_NO = cld.TSTM_NO
            AND co.BRCD = cld.BRCD
            SET
                co.BDGT_ITEX_FRCS_CON_HIT_YN =
                CASE
                WHEN co.BDGT_ITEX_FRCS_CON_HIT_YN IS NULL THEN
                CASE
                WHEN INSTR(co.BDGT_ITEX_FRCS_CON, cld.BDMN_ITEX_MNGM_NO) > 0 THEN 'Y'
                ELSE 'N'
        END
        ELSE co.BDGT_ITEX_FRCS_CON_HIT_YN
        END
        ,
            co.BDGT_BSNS_FRCS_CON_HIT_YN =
            CASE
                WHEN co.BDGT_BSNS_FRCS_CON_HIT_YN IS NULL THEN
                    CASE
                        WHEN INSTR(co.BDGT_BSNS_FRCS_CON, CONCAT(cld.BRCD, '-', cld.BDGT_BSNS_FRCS_CON)) > 0 THEN 'Y'
                        ELSE 'N'
        END
        ELSE co.BDGT_BSNS_FRCS_CON_HIT_YN
        END
        ,
            co.BDGT_PRFR_RSN_FRCS_CON_HIT_YN =
            CASE
                WHEN co.BDGT_PRFR_RSN_FRCS_CON_HIT_YN IS NULL THEN
                    CASE
                        WHEN INSTR(co.BDGT_PRFR_RSN_FRCS_CON, TRIM(cld.BDGT_PRFR_RSN_FRCS_CON)) > 0 THEN 'Y'
                        ELSE 'N'
        END
        ELSE co.BDGT_PRFR_RSN_FRCS_CON_HIT_YN
        END
        WHERE co.BDGT_ITEX_FRCS_CON_HIT_YN IS NULL
           OR co.BDGT_BSNS_FRCS_CON_HIT_YN IS NULL
           OR co.BDGT_PRFR_RSN_FRCS_CON_HIT_YN IS NULL
    </update>

    <select id="getUserUsageStat" resultType="UserStatusStatInfo">
        SELECT
            co.RSRE_YMD,
            co.HDQR_BOB_DCD,
            COUNT(*) AS total,
            SUM(CASE WHEN INSTR(co.BDGT_ITEX_FRCS_CON, cd.BDMN_ITEX_MNGM_NO) > 0 THEN 1 ELSE 0 END) AS hitCnt1,
            SUM(CASE WHEN INSTR(co.BDGT_BSNS_FRCS_CON, CONCAT(cd.BRCD, '-', cd.BDGT_BSNS_FRCS_CON)) > 0 THEN 1 ELSE 0 END) AS hitCnt2,
            SUM(CASE WHEN INSTR(co.BDGT_PRFR_RSN_FRCS_CON, TRIM(cd.BDGT_PRFR_RSN_FRCS_CON)) > 0 THEN 1 ELSE 0 END) AS hitCnt3,
            SUM(CASE WHEN INSTR(co.BDGT_ITEX_FRCS_CON, cd.BDMN_ITEX_MNGM_NO) > 0 AND INSTR(co.BDGT_BSNS_FRCS_CON, CONCAT(cd.BRCD, '-', cd.BDGT_BSNS_FRCS_CON)) > 0 THEN 1 ELSE 0 END) AS hitCnt4,
            SUM(CASE WHEN cd.ARIF_MDL_USE_YN = 'Y' THEN 1 ELSE 0 END) AS arinUseCnt,
            IFNULL(totalOut.totalOutCnt, 0) AS totalOutputCnt
        FROM CARD_OUTPUT co
        INNER JOIN CARD_LEARNING_DATA cd
        ON co.TSTM_YMD = cd.TSTM_YMD
        AND co.TSTM_NO = cd.TSTM_NO
        AND co.BRCD = cd.BRCD
        LEFT JOIN (
            SELECT
            co.RSRE_YMD,
            COUNT(*) AS totalOutCnt
            FROM CARD_OUTPUT co
            GROUP BY co.RSRE_YMD
            ) totalOut ON co.RSRE_YMD = totalOut.RSRE_YMD
        WHERE
            (co.BDGT_ITEX_FRCS_CON_HIT_YN IS NULL
            OR co.BDGT_BSNS_FRCS_CON_HIT_YN IS NULL
            OR co.BDGT_PRFR_RSN_FRCS_CON_HIT_YN IS NULL)
        GROUP BY co.RSRE_YMD, co.HDQR_BOB_DCD
    </select>

    <select id="existsUserUsageStat" parameterType="UserStatusStatInfo" resultType="int">
        SELECT COUNT(*) FROM AI_PRFR_STAT
        WHERE TYPE = #{type}
          AND BDGT_PRFR_YMD = #{rsreYmd}
          AND HDQR_BOB_DCD = #{hdqrBobDcd}
    </select>

    <update id="updateUserUsageStat" parameterType="UserStatusStatInfo">
        UPDATE USER_USAGE_STAT
        SET TOTAL = #{total},
            HIT_CNT1 = #{hitCnt1},
            HIT_CNT2 = #{hitCnt2},
            HIT_CNT3 = #{hitCnt3},
            HIT_CNT4 = #{hitCnt4},
            ARIN_USE_CNT = #{arinUseCnt},
            TOTAL_OUTPUT_CNT = #{totalOutputCnt}
        WHERE TYPE = #{type}
          AND RSRE_YMD = #{rsreYmd}
          AND HDQR_BOB_DCD = #{hdqrBobDcd}
    </update>

    <insert id="insertUserUsageStat" parameterType="UserStatusStatInfo">
        INSERT INTO USER_USAGE_STAT (
            TYPE, RSRE_YMD, RSRE_YM, RSRE_Y,
            HDQR_BOB_DCD, TOTAL, HIT_CNT1, HIT_CNT2, HIT_CNT3, HIT_CNT4, ARIN_USE_CNT, TOTAL_OUTPUT_CNT
        ) VALUES (
             #{type}, #{rsreYmd}, SUBSTRING(#{rsreYmd},1,6), SUBSTRING(#{rsreYmd},1,4),
             #{hdqrBobDcd}, #{total}, #{hitCnt1}, #{hitCnt2}, #{hitCnt3}, #{hitCnt4}, #{arinUseCnt}, #{totalOutputCnt}
         )
    </insert>

</mapper>